setup.cfg
setup.py
STLLock.egg-info/PKG-INFO
STLLock.egg-info/SOURCES.txt
STLLock.egg-info/dependency_links.txt
STLLock.egg-info/not-zip-safe
STLLock.egg-info/top_level.txt
stlock/__init__.py
stlock/stlock.py